get_geckodriver/__init__.py
get_geckodriver/cli.py
get_geckodriver/compile_utils.py
get_geckodriver/core.py
get_geckodriver/errors.py
get_geckodriver/reactos_shim.py
get_geckodriver-0.2.1.dist-info/COPYING
get_geckodriver-0.2.1.dist-info/METADATA
get_geckodriver-0.2.1.dist-info/WHEEL
get_geckodriver-0.2.1.dist-info/entry_points.txt
get_geckodriver-0.2.1.dist-info/top_level.txt
get_geckodriver-0.2.1.dist-info/RECORD
