Metadata-Version: 2.1
Name: get-geckodriver
Version: 0.2.1
Summary: Automatically install geckodriver, compile if required.
Home-page: https://codeberg.org/Eadaen1/get-geckodriver
Author: Eadaen
Author-email: eadaen@protonmail.com
License: GNU AGPL-3.0-or-later
Keywords: geckodriver selenium splinter
Platform: UNKNOWN
Classifier: Development Status :: 1 - Planning
Classifier: Topic :: Software Development :: Testing
Classifier: Topic :: System :: Installation/Setup
Classifier: Topic :: Software Development :: Libraries :: Python Modules
Classifier: License :: OSI Approved :: GNU Affero General Public License v3
Classifier: Programming Language :: Python :: 3 :: Only
Classifier: Programming Language :: Python :: 3.4
Classifier: Programming Language :: Python :: 3.6
Classifier: Programming Language :: Python :: 3.7
Classifier: Programming Language :: Python :: 3.8
Classifier: Operating System :: POSIX :: Linux
Classifier: Operating System :: MacOS :: MacOS X
Classifier: Operating System :: Microsoft :: Windows 
Classifier: Operating System :: POSIX :: BSD
Classifier: Operating System :: Unix
Classifier: Operating System :: Other OS
Classifier: Operating System :: Android
Requires-Python: >=3.4
